{
    "name": "Navigator Net",
    "build": {
        "dockerfile": "Dockerfile"
    },
    "runArgs": [
        "--gpus",
        "all"
    ],
    "workspaceFolder": "/workspace",
    "workspaceMount": "source=${localWorkspaceFolder},target=/workspace,type=bind",
    "forwardPorts": [
        9090
    ],
    "customizations": {
        "vscode": {
            "extensions": [
                "ms-python.python",
                "ms-python.vscode-pylance",
                "ms-iot.vscode-ros",
                "ms-vscode.cpptools",
                "charliermarsh.ruff",
                "ms-python.mypy-type-checker"
            ],
            "settings": {
                "python.defaultInterpreterPath": "/usr/bin/python3.10",
                "python.testing.pytestEnabled": true,
                "python.testing.unittestEnabled": false,
                "[python]": {
                    "editor.defaultFormatter": "charliermarsh.ruff",
                    "editor.formatOnSave": true,
                    "editor.codeActionsOnSave": {
                        "source.organizeImports": "explicit"
                    }
                }
            }
        }
    },
    "postCreateCommand": "apt-get update && rosdep update && rosdep install --from-paths src --ignore-src -y && uv pip install --system 'setuptools==58.2.0' && colcon build --symlink-install",
    "postStartCommand": "bash -c 'source /opt/ros/humble/setup.bash && nohup ros2 launch rosbridge_server rosbridge_websocket_launch.xml > /workspace/rosbridge.log 2>&1 &'"
}